camel/__init__.py
camel/camel_.py
Curvature_CAMEL-0.1.1.dist-info/METADATA
Curvature_CAMEL-0.1.1.dist-info/WHEEL
Curvature_CAMEL-0.1.1.dist-info/top_level.txt
Curvature_CAMEL-0.1.1.dist-info/RECORD
