Metadata-Version: 2.1
Name: Curvature-CAMEL
Version: 0.1.1
Summary: A brief description of CAMEL
Home-page: https://github.com/yourusername/camel
Author: Your Name
Author-email: your.email@example.com
Classifier: Programming Language :: Python :: 3
Classifier: License :: OSI Approved :: MIT License
Classifier: Operating System :: OS Independent
Requires-Python: >=3.6
Requires-Dist: numba
Requires-Dist: numpy
Requires-Dist: pynndescent
Requires-Dist: scikit-learn
Requires-Dist: scipy
